<?xml version="1.0" encoding="UTF-8"?><record_update table="sysevent_register">
    <sysevent_register action="INSERT_OR_UPDATE">
        <caller_access/>
        <derived_priority>100</derived_priority>
        <description/>
        <event_name>x_snc_plant_mgmt.plantWatered</event_name>
        <fired_by/>
        <priority>100</priority>
        <queue/>
        <suffix>plantWatered</suffix>
        <sys_class_name>sysevent_register</sys_class_name>
        <sys_created_by>admin</sys_created_by>
        <sys_created_on>2024-10-29 05:35:55</sys_created_on>
        <sys_id>fb79bf9dc3619a103ac9f0477d013140</sys_id>
        <sys_mod_count>0</sys_mod_count>
        <sys_name>x_snc_plant_mgmt.plantWatered</sys_name>
        <sys_package display_value="Plant Management" source="x_snc_plant_mgmt">9c697d609329ca10c7067a418bba1022</sys_package>
        <sys_policy/>
        <sys_scope display_value="Plant Management">9c697d609329ca10c7067a418bba1022</sys_scope>
        <sys_update_name>sysevent_register_fb79bf9dc3619a103ac9f0477d013140</sys_update_name>
        <sys_updated_by>admin</sys_updated_by>
        <sys_updated_on>2024-10-29 05:35:55</sys_updated_on>
        <table>x_snc_plant_mgmt_plants</table>
    </sysevent_register>
</record_update>
